{
  "project_info": {
    "project_number": "622805901370",
    "project_id": "lexical-theory-185706"
  },
  "client": [
    {
      "client_info": {
        "mobilesdk_app_id": "1:622805901370:android:7f33e98d26539be5",
        "android_client_info": {
          "package_name": "banyan.com.awesomebusiness"
        }
      },
      "oauth_client": [
        {
          "client_id": "622805901370-2g5696c3e717voe8jf0rsld3cl4s9dee.apps.googleusercontent.com",
          "client_type": 3
        },
        {
          "client_id": "622805901370-opo0o925p0dpjo394tt6gidcoilm2nap.apps.googleusercontent.com",
          "client_type": 1,
          "android_info": {
            "package_name": "banyan.com.awesomebusiness",
            "certificate_hash": "3ef7e29815a277fe1346b1e51022f182b802968a"
          }
        }
      ],
      "api_key": [
        {
          "current_key": "AIzaSyBWEX76Bi7MUYKxytcaR2fgEeFl4NKQfEU"
        }
      ],
      "services": {
        "analytics_service": {
          "status": 1
        },
        "appinvite_service": {
          "status": 1,
          "other_platform_oauth_client": []
        },
        "ads_service": {
          "status": 1
        }
      }
    }
  ],
  "configuration_version": "1"
}